odoo8_addon_account_cost_center-8.0.1.0.0-py2.7-nspkg.pth
odoo_addons/account_cost_center/__openerp__.py
odoo_addons/account_cost_center/__init__.py
odoo_addons/account_cost_center/README.rst
odoo_addons/account_cost_center/security/ir.model.access.csv
odoo_addons/account_cost_center/models/account_move_line.py
odoo_addons/account_cost_center/models/account_invoice_report.py
odoo_addons/account_cost_center/models/account_invoice.py
odoo_addons/account_cost_center/models/account_cost_center.py
odoo_addons/account_cost_center/models/__init__.py
odoo_addons/account_cost_center/models/account_invoice_line.py
odoo_addons/account_cost_center/views/account_move.xml
odoo_addons/account_cost_center/views/account_invoice.xml
odoo_addons/account_cost_center/views/account_cost_center.xml
odoo_addons/account_cost_center/views/account_move_line.xml
odoo_addons/account_cost_center/views/account_invoice_report.xml
odoo_addons/account_cost_center/static/description/index.html
odoo_addons/account_cost_center/static/description/account_costcenter_3.png
odoo_addons/account_cost_center/static/description/account_costcenter_2.png
odoo_addons/account_cost_center/static/description/account_costcenter_1.png
odoo8_addon_account_cost_center-8.0.1.0.0.dist-info/top_level.txt
odoo8_addon_account_cost_center-8.0.1.0.0.dist-info/WHEEL
odoo8_addon_account_cost_center-8.0.1.0.0.dist-info/RECORD
odoo8_addon_account_cost_center-8.0.1.0.0.dist-info/metadata.json
odoo8_addon_account_cost_center-8.0.1.0.0.dist-info/DESCRIPTION.rst
odoo8_addon_account_cost_center-8.0.1.0.0.dist-info/METADATA
odoo8_addon_account_cost_center-8.0.1.0.0.dist-info/namespace_packages.txt
